alsaker_rg/__init__.py
alsaker_rg/estimation.py
alsaker_rg-1.0.0.dist-info/licenses/LICENSE
alsaker_rg-1.0.0.dist-info/METADATA
alsaker_rg-1.0.0.dist-info/WHEEL
alsaker_rg-1.0.0.dist-info/top_level.txt
alsaker_rg-1.0.0.dist-info/RECORD
