Metadata-Version: 2.4
Name: alsaker-rg
Version: 1.0.0
Summary: Statistical estimation of radius of gyration from SAXS data
Author: Cody Alsaker, F. Jay Breidt, Mark J. van der Woerd
Maintainer-email: biosaxs-dev <biosaxs-dev@github.com>
License-Expression: GPL-3.0-or-later
Project-URL: Homepage, https://github.com/biosaxs-dev/alsaker-rg
Project-URL: Documentation, https://github.com/biosaxs-dev/alsaker-rg#readme
Project-URL: Repository, https://github.com/biosaxs-dev/alsaker-rg
Project-URL: Bug Tracker, https://github.com/biosaxs-dev/alsaker-rg/issues
Project-URL: Original R Code, https://mountainscholar.org/items/4c08f6d5-0f9b-4d45-a35a-ad39b59d3161
Project-URL: Paper, https://doi.org/10.1080/01621459.2017.1408467
Keywords: SAXS,small-angle x-ray scattering,radius of gyration,structural biology,biophysics,Guinier analysis,protein structure
Classifier: Development Status :: 5 - Production/Stable
Classifier: Intended Audience :: Science/Research
Classifier: Programming Language :: Python :: 3
Classifier: Programming Language :: Python :: 3.8
Classifier: Programming Language :: Python :: 3.9
Classifier: Programming Language :: Python :: 3.10
Classifier: Programming Language :: Python :: 3.11
Classifier: Programming Language :: Python :: 3.12
Classifier: Topic :: Scientific/Engineering :: Bio-Informatics
Classifier: Topic :: Scientific/Engineering :: Chemistry
Classifier: Topic :: Scientific/Engineering :: Physics
Classifier: Operating System :: OS Independent
Requires-Python: >=3.8
License-File: LICENSE
Requires-Dist: numpy>=1.20.0
Requires-Dist: scipy>=1.7.0
Requires-Dist: matplotlib>=3.3.0
Requires-Dist: pandas>=1.3.0
Requires-Dist: statsmodels>=0.13.0
Provides-Extra: changepoint
Requires-Dist: ruptures>=1.1.0; extra == "changepoint"
Provides-Extra: dev
Requires-Dist: pytest>=7.0; extra == "dev"
Requires-Dist: pytest-cov>=3.0; extra == "dev"
Requires-Dist: black>=22.0; extra == "dev"
Requires-Dist: isort>=5.10; extra == "dev"
Requires-Dist: flake8>=4.0; extra == "dev"
Requires-Dist: mypy>=0.950; extra == "dev"
Provides-Extra: all
Requires-Dist: ruptures>=1.1.0; extra == "all"
Requires-Dist: pytest>=7.0; extra == "all"
Requires-Dist: pytest-cov>=3.0; extra == "all"
Dynamic: license-file
